pystanley/__init__.py
pystanley/__main__.py
pystanley/cache.py
pystanley/select_response_schema.json
pystanley/subscribe_response_schema.json
pystanley/types.py
pystanley/validation.py
pystanley/transport/__init__.py
pystanley/transport/aiohttp.py
pystanley-0.1.0.dist-info/METADATA
pystanley-0.1.0.dist-info/WHEEL
pystanley-0.1.0.dist-info/entry_points.txt
pystanley-0.1.0.dist-info/top_level.txt
pystanley-0.1.0.dist-info/RECORD
