Metadata-Version: 2.1
Name: pystanley
Version: 0.1.0
Summary: Interface to Stanley time-series database
Home-page: https://gitlab.com/claudiomattera/pystanley/
Author: Claudio Giovanni Mattera
Author-email: claudio@mattera.it
License: MIT
Platform: UNKNOWN
Requires-Dist: pandas
Requires-Dist: aiohttp
Requires-Dist: websockets
Requires-Dist: appdirs
Requires-Dist: jsonschema
Requires-Dist: iso8601
Provides-Extra: plot
Requires-Dist: matplotlib ; extra == 'plot'
